mkdocs_ringcentral_api_index_plugin/__init__.py
mkdocs_ringcentral_api_index_plugin/plugin.py
mkdocs_ringcentral_api_index-0.1.7.dist-info/LICENSE
mkdocs_ringcentral_api_index-0.1.7.dist-info/METADATA
mkdocs_ringcentral_api_index-0.1.7.dist-info/WHEEL
mkdocs_ringcentral_api_index-0.1.7.dist-info/entry_points.txt
mkdocs_ringcentral_api_index-0.1.7.dist-info/top_level.txt
mkdocs_ringcentral_api_index-0.1.7.dist-info/RECORD
